fastapi_users_db_beanie/__init__.py
fastapi_users_db_beanie/access_token.py
fastapi_users_db_beanie/py.typed
fastapi_users_db_beanie-2.0.0.dist-info/METADATA
fastapi_users_db_beanie-2.0.0.dist-info/WHEEL
fastapi_users_db_beanie-2.0.0.dist-info/licenses/LICENSE
fastapi_users_db_beanie-2.0.0.dist-info/RECORD
